smallestai/__init__.py
smallestai/atoms/__init__.py
smallestai/atoms/api_client.py
smallestai/atoms/api_response.py
smallestai/atoms/atoms_client.py
smallestai/atoms/configuration.py
smallestai/atoms/exceptions.py
smallestai/atoms/py.typed
smallestai/atoms/rest.py
smallestai/atoms/agent/context.py
smallestai/atoms/agent/events.py
smallestai/atoms/agent/server.py
smallestai/atoms/agent/session.py
smallestai/atoms/agent/task_manager.py
smallestai/atoms/agent/type.py
smallestai/atoms/agent/clients/__init__.py
smallestai/atoms/agent/clients/base.py
smallestai/atoms/agent/clients/openai.py
smallestai/atoms/agent/clients/types.py
smallestai/atoms/agent/nodes/__init__.py
smallestai/atoms/agent/nodes/background_agent.py
smallestai/atoms/agent/nodes/base.py
smallestai/atoms/agent/nodes/output_agent.py
smallestai/atoms/agent/tools/__init__.py
smallestai/atoms/agent/tools/decorator.py
smallestai/atoms/agent/tools/registry.py
smallestai/atoms/agent/tools/schema.py
smallestai/atoms/api/__init__.py
smallestai/atoms/api/agent_templates_api.py
smallestai/atoms/api/agents_api.py
smallestai/atoms/api/calls_api.py
smallestai/atoms/api/campaigns_api.py
smallestai/atoms/api/knowledge_base_api.py
smallestai/atoms/api/logs_api.py
smallestai/atoms/api/organization_api.py
smallestai/atoms/api/user_api.py
smallestai/atoms/models/__init__.py
smallestai/atoms/models/agent_agent_id_webhook_subscriptions_delete200_response.py
smallestai/atoms/models/agent_agent_id_webhook_subscriptions_get200_response.py
smallestai/atoms/models/agent_agent_id_webhook_subscriptions_get404_response.py
smallestai/atoms/models/agent_agent_id_webhook_subscriptions_post201_response.py
smallestai/atoms/models/agent_agent_id_webhook_subscriptions_post400_response.py
smallestai/atoms/models/agent_agent_id_webhook_subscriptions_post_request.py
smallestai/atoms/models/agent_dto.py
smallestai/atoms/models/agent_dto_language.py
smallestai/atoms/models/agent_dto_language_switching.py
smallestai-4.2.1.dist-info/licenses/LICENSE
smallestai-4.2.1.dist-info/METADATA
smallestai-4.2.1.dist-info/WHEEL
smallestai-4.2.1.dist-info/entry_points.txt
smallestai-4.2.1.dist-info/top_level.txt
smallestai-4.2.1.dist-info/RECORD
