Metadata-Version: 2.4
Name: smallestai
Version: 4.2.1
Summary: Official Python client for the Smallest AI API
Author-email: Smallest <support@smallest.ai>
License: MIT
Project-URL: Homepage, https://github.com/smallest-inc/smallest-python-sdk
Keywords: smallest,smallest.ai,tts,text-to-speech,waves,atoms
Classifier: Intended Audience :: Developers
Classifier: License :: OSI Approved :: MIT License
Classifier: Programming Language :: Python :: 3
Requires-Python: >=3.9
License-File: LICENSE
Requires-Dist: aiohttp
Requires-Dist: aiofiles
Requires-Dist: requests
Requires-Dist: pydub
Requires-Dist: websocket-client
Requires-Dist: urllib3<3.0.0,>=1.25.3
Requires-Dist: python-dateutil>=2.8.2
Requires-Dist: pydantic>=2
Requires-Dist: typing-extensions>=4.7.1
Requires-Dist: audioop-lts; python_version >= "3.13"
Requires-Dist: loguru>=0.7.0
Requires-Dist: fastapi>=0.115.0
Requires-Dist: httpx>=0.28.1
Requires-Dist: python-dotenv>=1.2.1
Requires-Dist: questionary>=2.1.1
Requires-Dist: rich>=14.2.0
Requires-Dist: tomli>=2.3.0
Requires-Dist: tomli-w>=1.2.0
Requires-Dist: typer>=0.20.0
Requires-Dist: uvicorn>=0.32.0
Requires-Dist: websockets>=14.0
Requires-Dist: openai>=2.14.0
Provides-Extra: test
Requires-Dist: jiwer; extra == "test"
Requires-Dist: pytest>=7.2.1; extra == "test"
Requires-Dist: pytest-asyncio; extra == "test"
Requires-Dist: deepgram-sdk; extra == "test"
Requires-Dist: pytest-cov>=2.8.1; extra == "test"
Requires-Dist: tox>=3.9.0; extra == "test"
Requires-Dist: flake8>=4.0.0; extra == "test"
Requires-Dist: types-python-dateutil>=2.8.19.14; extra == "test"
Requires-Dist: mypy>=1.5; extra == "test"
Dynamic: license-file
